wikipack/commands/__init__.py
wikipack/events/__init__.py
wikipack/stars/__init__.py
wikipack/stars/api_wiki.py
wikipack/stars/api_wiki_list.py
wikipack/tables/__init__.py
wikipack/tables/wikideletion.py
wikipack/tables/wikirevision.py
wikipack/version.py
wikipack-1.2.0.dist-info/WHEEL
wikipack-1.2.0.dist-info/METADATA
wikipack-1.2.0.dist-info/RECORD
