Metadata-Version: 2.1
Name: wikipack
Version: 1.2.0
Summary: A Wiki for Royalnet
Home-page: https://github.com/Steffo99/wikipack/
Author: Stefano Pigozzi
Author-email: ste.pigozzi@gmail.com
Requires-Python: >=3.8,<4.0
Classifier: Development Status :: 3 - Alpha
Classifier: License :: OSI Approved :: GNU Affero General Public License v3 or later (AGPLv3+)
Classifier: Operating System :: OS Independent
Classifier: Programming Language :: Python :: 3
Classifier: Programming Language :: Python :: 3.8
Requires-Dist: royalnet[alchemy_easy,constellation] (>=5.10.0,<5.11.0)
